aiooss2/__init__.py
aiooss2/adapter.py
aiooss2/api.py
aiooss2/exceptions.py
aiooss2/http.py
aiooss2/iterators.py
aiooss2/models.py
aiooss2/multipart.py
aiooss2/py.typed
aiooss2/resumable.py
aiooss2/utils.py
aiooss2-0.2.11.dist-info/LICENSE
aiooss2-0.2.11.dist-info/METADATA
aiooss2-0.2.11.dist-info/WHEEL
aiooss2-0.2.11.dist-info/top_level.txt
aiooss2-0.2.11.dist-info/RECORD
