Metadata-Version: 2.1
Name: aiooss2
Version: 0.2.11
Summary: Async client for aliyun OSS(Object Storage Service) using oss2 and aiohttp/asyncio
Home-page: https://github.com/karajan1001/aiooss2
Maintainer-email: mishanyo1001@gmail.com
License: Apache-2.0
Keywords: "oss,aio"
Platform: any
Classifier: Programming Language :: Python :: 3
Classifier: Programming Language :: Python :: 3.8
Classifier: Programming Language :: Python :: 3.9
Classifier: Programming Language :: Python :: 3.10
Classifier: Programming Language :: Python :: 3.11
Classifier: Development Status :: 3 - Alpha
Requires-Python: >=3.8
License-File: LICENSE
Requires-Dist: aiohttp<4,>=3.9.1
Requires-Dist: oss2==2.18.4
Provides-Extra: tests
Requires-Dist: pytest==7.2.0; extra == "tests"
Requires-Dist: pytest-sugar==0.9.5; extra == "tests"
Requires-Dist: pytest-cov==3.0.0; extra == "tests"
Requires-Dist: pytest-mock==3.8.2; extra == "tests"
Requires-Dist: pylint==2.15.0; extra == "tests"
Requires-Dist: pylint-pytest==1.1.7; extra == "tests"
Requires-Dist: mypy==0.971; extra == "tests"
Provides-Extra: dev
Requires-Dist: pytest==7.2.0; extra == "dev"
Requires-Dist: pytest-sugar==0.9.5; extra == "dev"
Requires-Dist: pytest-cov==3.0.0; extra == "dev"
Requires-Dist: pytest-mock==3.8.2; extra == "dev"
Requires-Dist: pylint==2.15.0; extra == "dev"
Requires-Dist: pylint-pytest==1.1.7; extra == "dev"
Requires-Dist: mypy==0.971; extra == "dev"
Requires-Dist: nox==2024.3.2; extra == "dev"
